pyfresco/RGBmap.py
pyfresco/SpectraAnalysis.py
pyfresco/SpectraExtract.py
pyfresco/SpectraNorm.py
pyfresco/__init__.py
pyfresco-0.1.3.dist-info/licenses/LICENSE.txt
pyfresco-0.1.3.dist-info/METADATA
pyfresco-0.1.3.dist-info/WHEEL
pyfresco-0.1.3.dist-info/top_level.txt
pyfresco-0.1.3.dist-info/RECORD
