Metadata-Version: 2.4
Name: pyFRESCO
Version: 0.1.3
Author-email: Marco Baroni <mbaroni96@gmail.com>, Beatrice Baschetti <beatrice.baschetti@inaf.it>
License: MIT
Project-URL: Source, https://github.com/MarcoBaroni/pyfresco
Requires-Python: >=3.6
License-File: LICENSE.txt
Requires-Dist: kneed>=0.8.5
Requires-Dist: matplotlib>=3.7.5
Requires-Dist: numpy>=1.24.4
Requires-Dist: pandas>=2.0.3
Requires-Dist: rasterio>=1.3.10
Requires-Dist: scipy>=1.10.1
Requires-Dist: spectral>=0.23.1
Requires-Dist: torch>=2.4.0
Dynamic: license-file
